{
  "default": [
    {
      "expression": "*.ebay-kleinanzeigen.de",
      "listType": "WHITE",
      "storeId": "default",
      "id": "H1k1GfyJQ",
      "cookieNames": []
    },
    {
      "expression": "*.gabbbocakeomblphkmmnoamkioajlkfo",
      "listType": "WHITE",
      "storeId": "default",
      "id": "B1d9UMJJ7",
      "cookieNames": []
    },
    {
      "expression": "*.github.com",
      "listType": "WHITE",
      "storeId": "default",
      "id": "BkMszf6Af",
      "cookieNames": []
    },
    {
      "expression": "*.humblebundle.com",
      "listType": "WHITE",
      "storeId": "default",
      "id": "B1vGWkJJX",
      "cookieNames": []
    },
    {
      "expression": "*.mee6.xyz",
      "listType": "WHITE",
      "storeId": "default",
      "id": "rJshQey1m",
      "cookieNames": []
    },
    {
      "expression": "*.wordpress.com",
      "listType": "WHITE",
      "storeId": "default",
      "id": "Hyri-JJJ7",
      "cookieNames": []
    },
    {
      "expression": "gog",
      "storeId": "default",
      "listType": "WHITE",
      "id": "HJY_TZ1kX",
      "cookieNames": []
    },
    {
      "expression": "*.1blocker.com",
      "listType": "GREY",
      "storeId": "default",
      "id": "Sye-XTQgJQ",
      "cookieNames": []
    },
    {
      "expression": "*.4pda.ru",
      "listType": "GREY",
      "storeId": "default",
      "id": "SJHOoZkJ7",
      "cookieNames": []
    },
    {
      "expression": "*.abc.xyz",
      "listType": "GREY",
      "storeId": "default",
      "id": "Hyp5aGlym",
      "cookieNames": []
    },
    {
      "expression": "*.adtidy.org",
      "listType": "GREY",
      "storeId": "default",
      "id": "SJ7VajR0f",
      "cookieNames": []
    },
    {
      "expression": "*.alibabacloud.com",
      "listType": "GREY",
      "storeId": "default",
      "id": "By_GiDaRz",
      "cookieNames": []
    },
    {
      "expression": "*.anwalt.de",
      "listType": "GREY",
      "storeId": "default",
      "id": "B1L3WfgJQ",
      "cookieNames": []
    },
    {
      "expression": "*.anwaltssuche.de",
      "listType": "GREY",
      "storeId": "default",
      "id": "rJDwfGl1X",
      "cookieNames": []
    },
    {
      "expression": "*.anwaltsverzeichnis.de",
      "listType": "GREY",
      "storeId": "default",
      "id": "BJ9c-Gly7",
      "cookieNames": []
    },
    {
      "expression": "*.arestwo.org",
      "listType": "GREY",
      "storeId": "default",
      "id": "ByQ-OeyJ7",
      "cookieNames": []
    },
    {
      "expression": "*.backstage.1blocker.com",
      "listType": "GREY",
      "storeId": "default",
      "id": "BkbQpmlJX",
      "cookieNames": []
    },
    {
      "expression": "*.bitchute.com",
      "listType": "GREY",
      "storeId": "default",
      "id": "HymB4zkkQ",
      "cookieNames": []
    },
    {
      "expression": "*.blog.malwarebytes.com",
      "listType": "GREY",
      "storeId": "default",
      "id": "ryXqIZJJQ",
      "cookieNames": []
    },
    {
      "expression": "*.bringingprivacyback.com",
      "listType": "GREY",
      "storeId": "default",
      "id": "rkZoSzkym",
      "cookieNames": []
    },
    {
      "expression": "*.bugs.chromium.org",
      "listType": "GREY",
      "storeId": "default",
      "id": "rJwY_eykm",
      "cookieNames": []
    },
    {
      "expression": "*.cdnjs.cloudflare.com",
      "listType": "GREY",
      "storeId": "default",
      "id": "rJarlbgkX",
      "cookieNames": []
    },
    {
      "expression": "*.chromium.org",
      "listType": "GREY",
      "storeId": "default",
      "id": "SyxwFOekJQ",
      "cookieNames": []
    },
    {
      "expression": "*.chromium.woolyss.com",
      "listType": "GREY",
      "storeId": "default",
      "id": "S1vKYxJym",
      "cookieNames": []
    },
    {
      "expression": "*.cloudflare.com",
      "listType": "GREY",
      "storeId": "default",
      "id": "Sy2rgWxk7",
      "cookieNames": []
    },
    {
      "expression": "*.cloudforge.com",
      "listType": "GREY",
      "storeId": "default",
      "id": "H1N7zH0Cf",
      "cookieNames": []
    },
    {
      "expression": "*.d.tube",
      "listType": "GREY",
      "storeId": "default",
      "id": "H1mU4Gk17",
      "cookieNames": []
    },
    {
      "expression": "*.dailyuploads.net",
      "listType": "GREY",
      "storeId": "default",
      "id": "SJlf7uaAM",
      "cookieNames": []
    },
    {
      "expression": "*.datenschmutz.net",
      "listType": "GREY",
      "storeId": "default",
      "id": "rkKvAflk7",
      "cookieNames": []
    },
    {
      "expression": "*.discordapp.com",
      "listType": "GREY",
      "storeId": "default",
      "id": "SyeXjwR0z",
      "cookieNames": []
    },
    {
      "expression": "*.discordbots.org",
      "listType": "GREY",
      "storeId": "default",
      "id": "H1F6flyyQ",
      "cookieNames": []
    },
    {
      "expression": "*.docs.microsoft.com",
      "listType": "GREY",
      "storeId": "default",
      "id": "H1-vGiRCG",
      "cookieNames": []
    },
    {
      "expression": "*.docviewer.yandex.com",
      "listType": "GREY",
      "storeId": "default",
      "id": "SJUP9Ha0G",
      "cookieNames": []
    },
    {
      "expression": "*.douploads.com",
      "listType": "GREY",
      "storeId": "default",
      "id": "Syn6G_aRM",
      "cookieNames": []
    },
    {
      "expression": "*.easyjet.com",
      "listType": "GREY",
      "storeId": "default",
      "id": "SJxHFxk1X",
      "cookieNames": []
    },
    {
      "expression": "*.ebay.de",
      "listType": "GREY",
      "storeId": "default",
      "id": "rynTKzg1Q",
      "cookieNames": []
    },
    {
      "expression": "*.en.wikichip.org",
      "listType": "GREY",
      "storeId": "default",
      "id": "B1NgIP0CM",
      "cookieNames": []
    },
    {
      "expression": "*.filecroco.com",
      "listType": "GREY",
      "storeId": "default",
      "id": "SkqYXsR0f",
      "cookieNames": []
    },
    {
      "expression": "*.fileflares.com",
      "listType": "GREY",
      "storeId": "default",
      "id": "rkXx-BTCM",
      "cookieNames": []
    },
    {
      "expression": "*.filterlists.com",
      "listType": "GREY",
      "storeId": "default",
      "id": "HyCX4dC0z",
      "cookieNames": []
    },
    {
      "expression": "*.filters.adtidy.org",
      "listType": "GREY",
      "storeId": "default",
      "id": "rJG4aiA0G",
      "cookieNames": []
    },
    {
      "expression": "*.forum.manjaro.org",
      "listType": "GREY",
      "storeId": "default",
      "id": "B1jx3JyJX",
      "cookieNames": []
    },
    {
      "expression": "*.forums.lanik.us",
      "listType": "GREY",
      "storeId": "default",
      "id": "SJlS2xyym",
      "cookieNames": []
    },
    {
      "expression": "*.fritz.box",
      "listType": "GREY",
      "storeId": "default",
      "id": "SJqKKYACf",
      "cookieNames": []
    },
    {
      "expression": "*.gitforwindows.org",
      "listType": "GREY",
      "storeId": "default",
      "id": "H1qavYCRM",
      "cookieNames": []
    },
    {
      "expression": "*.github.io",
      "listType": "GREY",
      "storeId": "default",
      "id": "Skz5HDpRf",
      "cookieNames": []
    },
    {
      "expression": "*.gizmodo.com",
      "listType": "GREY",
      "storeId": "default",
      "id": "BJ3dpfg17",
      "cookieNames": []
    },
    {
      "expression": "*.gog.com",
      "listType": "GREY",
      "storeId": "default",
      "id": "S1zOTb1yQ",
      "cookieNames": []
    },
    {
      "expression": "*.google.com",
      "listType": "GREY",
      "storeId": "default",
      "id": "SJe3GOpCG",
      "cookieNames": []
    },
    {
      "expression": "*.google.de",
      "listType": "GREY",
      "storeId": "default",
      "id": "Hk9nvYACM",
      "cookieNames": []
    },
    {
      "expression": "*.gskill.com",
      "listType": "GREY",
      "storeId": "default",
      "id": "HJ2IPO6Rz",
      "cookieNames": []
    },
    {
      "expression": "*.gskill.us",
      "listType": "GREY",
      "storeId": "default",
      "id": "ryNm_dpRM",
      "cookieNames": []
    },
    {
      "expression": "*.hartz.info",
      "listType": "GREY",
      "storeId": "default",
      "id": "rJEaifgkX",
      "cookieNames": []
    },
    {
      "expression": "*.hartz4.de",
      "listType": "GREY",
      "storeId": "default",
      "id": "rkO9zflJm",
      "cookieNames": []
    },
    {
      "expression": "*.heise.de",
      "listType": "GREY",
      "storeId": "default",
      "id": "rJLcB96CM",
      "cookieNames": []
    },
    {
      "expression": "*.helgeklein.com",
      "listType": "GREY",
      "storeId": "default",
      "id": "r1tRbYRAz",
      "cookieNames": []
    },
    {
      "expression": "*.help.cloudforge.com",
      "listType": "GREY",
      "storeId": "default",
      "id": "Sk77GHARM",
      "cookieNames": []
    },
    {
      "expression": "*.hosts-file.net",
      "listType": "GREY",
      "storeId": "default",
      "id": "H1QIKMJ1X",
      "cookieNames": []
    },
    {
      "expression": "*.i.redditmedia.com",
      "listType": "GREY",
      "storeId": "default",
      "id": "rJy6htACM",
      "cookieNames": []
    },
    {
      "expression": "*.imgur.com",
      "listType": "GREY",
      "storeId": "default",
      "id": "H1Wc6YCCz",
      "cookieNames": []
    },
    {
      "expression": "*.joinpeertube.org",
      "listType": "GREY",
      "storeId": "default",
      "id": "BJeEEM1yX",
      "cookieNames": []
    },
    {
      "expression": "*.keepass.info",
      "listType": "GREY",
      "storeId": "default",
      "id": "ryoMlMyJX",
      "cookieNames": []
    },
    {
      "expression": "*.lanik.us",
      "listType": "GREY",
      "storeId": "default",
      "id": "SyxgBnl1Jm",
      "cookieNames": []
    },
    {
      "expression": "*.malwarebytes.com",
      "listType": "GREY",
      "storeId": "default",
      "id": "r1N5Lbkym",
      "cookieNames": []
    },
    {
      "expression": "*.manjaro.org",
      "listType": "GREY",
      "storeId": "default",
      "id": "SJejx2kk1Q",
      "cookieNames": []
    },
    {
      "expression": "*.mediafire.com",
      "listType": "GREY",
      "storeId": "default",
      "id": "S18tDYpAf",
      "cookieNames": []
    },
    {
      "expression": "*.medium.com",
      "listType": "GREY",
      "storeId": "default",
      "id": "B1-1h8T0f",
      "cookieNames": []
    },
    {
      "expression": "*.microsoft.com",
      "listType": "GREY",
      "storeId": "default",
      "id": "BJeWUktpRM",
      "cookieNames": []
    },
    {
      "expression": "*.ncsc.gov.uk",
      "listType": "GREY",
      "storeId": "default",
      "id": "HJIXmcTCM",
      "cookieNames": []
    },
    {
      "expression": "*.nirsoft.net",
      "listType": "GREY",
      "storeId": "default",
      "id": "Bk1AIqAAz",
      "cookieNames": []
    },
    {
      "expression": "*.nmap.org",
      "listType": "GREY",
      "storeId": "default",
      "id": "H1_alqCAG",
      "cookieNames": []
    },
    {
      "expression": "*.notebookcheck.net",
      "listType": "GREY",
      "storeId": "default",
      "id": "r1NeQ-gJQ",
      "cookieNames": []
    },
    {
      "expression": "*.ntlite.com",
      "listType": "GREY",
      "storeId": "default",
      "id": "SJC2Jk117",
      "cookieNames": []
    },
    {
      "expression": "*.oo-software.com",
      "listType": "GREY",
      "storeId": "default",
      "id": "By9sgUT0z",
      "cookieNames": []
    },
    {
      "expression": "*.palant.de",
      "listType": "GREY",
      "storeId": "default",
      "id": "Hyj5HW117",
      "cookieNames": []
    },
    {
      "expression": "*.paulirish.github.io",
      "listType": "GREY",
      "storeId": "default",
      "id": "HJ-yuDpCf",
      "cookieNames": []
    },
    {
      "expression": "*.play.google.com",
      "listType": "GREY",
      "storeId": "default",
      "id": "rkkhf_6Cz",
      "cookieNames": []
    },
    {
      "expression": "*.pornhub.com",
      "listType": "GREY",
      "storeId": "default",
      "id": "BkUtjcaAf",
      "cookieNames": []
    },
    {
      "expression": "*.rackspace.com",
      "listType": "GREY",
      "storeId": "default",
      "id": "rJLGWs0AG",
      "cookieNames": []
    },
    {
      "expression": "*.re-volt.io",
      "listType": "GREY",
      "storeId": "default",
      "id": "H1gTVtZyJ7",
      "cookieNames": []
    },
    {
      "expression": "*.reddit.com",
      "listType": "GREY",
      "storeId": "default",
      "id": "HJiRhYAAz",
      "cookieNames": []
    },
    {
      "expression": "*.redditmedia.com",
      "listType": "GREY",
      "storeId": "default",
      "id": "HyeJT2FCAG",
      "cookieNames": []
    },
    {
      "expression": "*.rsload.net",
      "listType": "GREY",
      "storeId": "default",
      "id": "HJMh6cAAM",
      "cookieNames": []
    },
    {
      "expression": "*.rvgl.re-volt.io",
      "listType": "GREY",
      "storeId": "default",
      "id": "By64KZJJm",
      "cookieNames": []
    },
    {
      "expression": "*.sandboxie.com",
      "listType": "GREY",
      "storeId": "default",
      "id": "r1YN-9RRf",
      "cookieNames": []
    },
    {
      "expression": "*.scmagazineuk.com",
      "listType": "GREY",
      "storeId": "default",
      "id": "HyFscbxJm",
      "cookieNames": []
    },
    {
      "expression": "*.sheepy.pw",
      "listType": "GREY",
      "storeId": "default",
      "id": "HkXNBgyJm",
      "cookieNames": []
    },
    {
      "expression": "*.sites.google.com",
      "listType": "GREY",
      "storeId": "default",
      "id": "HJ76Bb1y7",
      "cookieNames": []
    },
    {
      "expression": "*.skidrowgamesreloaded.com",
      "listType": "GREY",
      "storeId": "default",
      "id": "SyI23bkkm",
      "cookieNames": []
    },
    {
      "expression": "*.slideme.org",
      "listType": "GREY",
      "storeId": "default",
      "id": "Bk8asZ117",
      "cookieNames": []
    },
    {
      "expression": "*.social.technet.microsoft.com",
      "listType": "GREY",
      "storeId": "default",
      "id": "r1RhxjARG",
      "cookieNames": []
    },
    {
      "expression": "*.softwareok.com",
      "listType": "GREY",
      "storeId": "default",
      "id": "ryCZEYpAG",
      "cookieNames": []
    },
    {
      "expression": "*.sourceforge.net",
      "listType": "GREY",
      "storeId": "default",
      "id": "S1GrE8pAz",
      "cookieNames": []
    },
    {
      "expression": "*.sourcegear.com",
      "listType": "GREY",
      "storeId": "default",
      "id": "B12HWd60G",
      "cookieNames": []
    },
    {
      "expression": "*.spideroak.com",
      "listType": "GREY",
      "storeId": "default",
      "id": "SkctHGkJm",
      "cookieNames": []
    },
    {
      "expression": "*.storesteampoweredcom",
      "listType": "GREY",
      "storeId": "default",
      "id": "S1fT2000G",
      "cookieNames": []
    },
    {
      "expression": "*.support.amd.com",
      "listType": "GREY",
      "storeId": "default",
      "id": "ry_Q5YRAz",
      "cookieNames": []
    },
    {
      "expression": "*.support.microsoft.com",
      "listType": "GREY",
      "storeId": "default",
      "id": "ryb8ytTCM",
      "cookieNames": []
    },
    {
      "expression": "*.support.rackspace.com",
      "listType": "GREY",
      "storeId": "default",
      "id": "SyBGbiACf",
      "cookieNames": []
    },
    {
      "expression": "*.teamos-hkrg.com",
      "listType": "GREY",
      "storeId": "default",
      "id": "H1vSX_A0z",
      "cookieNames": []
    },
    {
      "expression": "*.technipages.com",
      "listType": "GREY",
      "storeId": "default",
      "id": "BkJPiUT0M",
      "cookieNames": []
    },
    {
      "expression": "*.technitium.com",
      "listType": "GREY",
      "storeId": "default",
      "id": "rkXrOFA0f",
      "cookieNames": []
    },
    {
      "expression": "*.telerik.com",
      "listType": "GREY",
      "storeId": "default",
      "id": "r1-4xsRCM",
      "cookieNames": []
    },
    {
      "expression": "*.tenforums.com",
      "listType": "GREY",
      "storeId": "default",
      "id": "S1iOSFR0G",
      "cookieNames": []
    },
    {
      "expression": "*.textmechanic.com",
      "listType": "GREY",
      "storeId": "default",
      "id": "Bk-ec-kJQ",
      "cookieNames": []
    },
    {
      "expression": "*.uploadocean.com",
      "listType": "GREY",
      "storeId": "default",
      "id": "S1HjfYa0G",
      "cookieNames": []
    },
    {
      "expression": "*.uploads.to",
      "listType": "GREY",
      "storeId": "default",
      "id": "HJ1Lgek1m",
      "cookieNames": []
    },
    {
      "expression": "*.w3c.github.io",
      "listType": "GREY",
      "storeId": "default",
      "id": "HyWqrDaAG",
      "cookieNames": []
    },
    {
      "expression": "*.wikichip.org",
      "listType": "GREY",
      "storeId": "default",
      "id": "SJgVxLvRAG",
      "cookieNames": []
    },
    {
      "expression": "*.win-raid.com",
      "listType": "GREY",
      "storeId": "default",
      "id": "ry3l4BpRz",
      "cookieNames": []
    },
    {
      "expression": "*.winaero.com",
      "listType": "GREY",
      "storeId": "default",
      "id": "rykpyt6Rf",
      "cookieNames": []
    },
    {
      "expression": "*.winpcap.org",
      "listType": "GREY",
      "storeId": "default",
      "id": "Sy8lkoACz",
      "cookieNames": []
    },
    {
      "expression": "*.wj32.org",
      "listType": "GREY",
      "storeId": "default",
      "id": "rylbvrTAf",
      "cookieNames": []
    },
    {
      "expression": "*.woolyss.com",
      "listType": "GREY",
      "storeId": "default",
      "id": "BJgPKKlkJX",
      "cookieNames": []
    },
    {
      "expression": "docviewer.yandex.com",
      "listType": "GREY",
      "storeId": "default",
      "id": "H1g8D5SaRG",
      "cookieNames": []
    }
  ]
}